timechop/__init__.py
timechop/timechop.py
timechop/utils.py
timechop-1.0.0.dist-info/DESCRIPTION.rst
timechop-1.0.0.dist-info/METADATA
timechop-1.0.0.dist-info/RECORD
timechop-1.0.0.dist-info/WHEEL
timechop-1.0.0.dist-info/metadata.json
timechop-1.0.0.dist-info/top_level.txt
