Metadata-Version: 2.0
Name: timechop
Version: 1.0.0
Summary: Implements temporal validation for machine learning/
Home-page: https://github.com/dssg/timechop
Author: Center for Data Science and Public Policy
Author-email: datascifellows@gmail.com
License: BY DOWNLOADING timechop PROGRAM YOU AGREE TO THE FOLLOWING TERMS OF USE:
Requires-Dist: python-dateutil
